accessvis/__init__.py
accessvis/_version.py
accessvis/earth.py
accessvis/utils.py
accessvis/data/blank.png
accessvis/data/earth_shader.frag
accessvis/data/earth_shader.vert
accessvis/data/screen.frag
accessvis/data/screen.vert
accessvis/data/sea-water-1024x1024_gs.png
accessvis/data/sea-water_normals.png
accessvis/widgets/__init__.py
accessvis/widgets/calendar_widget.py
accessvis/widgets/clock_widget.py
accessvis/widgets/image_widget.py
accessvis/widgets/season_widget.py
accessvis/widgets/text_widget.py
accessvis/widgets/widget_base.py
accessvis-1.1.4.dist-info/licenses/LICENSE
accessvis-1.1.4.dist-info/METADATA
accessvis-1.1.4.dist-info/WHEEL
accessvis-1.1.4.dist-info/top_level.txt
accessvis-1.1.4.dist-info/RECORD
