Metadata-Version: 2.4
Name: accessvis
Version: 1.1.4
Summary: 3D visualisation tools and utilities for earth systems data
Author-email: Owen Kaluza <owen.kaluza@anu.edu.au>
Maintainer-email: Owen Kaluza <owen.kaluza@anu.edu.au>
License:                                  Apache License
Keywords: access-nri,3d-viz,visualisation
Classifier: Programming Language :: Python :: 3
Classifier: Programming Language :: Python :: 3 :: Only
Classifier: License :: OSI Approved :: Apache Software License
Classifier: Intended Audience :: Developers
Classifier: Intended Audience :: Science/Research
Classifier: Topic :: Multimedia :: Graphics :: 3D Rendering
Classifier: Topic :: Scientific/Engineering :: Visualization
Classifier: Development Status :: 3 - Alpha
Classifier: Programming Language :: C++
Classifier: Programming Language :: Python :: 3
Classifier: Programming Language :: Python :: 3.6
Classifier: Programming Language :: Python :: 3.7
Classifier: Programming Language :: Python :: 3.8
Classifier: Programming Language :: Python :: 3.9
Classifier: Programming Language :: Python :: 3.10
Classifier: Programming Language :: Python :: 3.11
Classifier: Programming Language :: Python :: 3.12
Classifier: Programming Language :: Python :: 3.13
Classifier: Programming Language :: Python :: 3 :: Only
Classifier: Framework :: Jupyter
Classifier: Framework :: IPython
Requires-Python: >=3.6
License-File: LICENSE
Requires-Dist: lavavu
Requires-Dist: pillow
Requires-Dist: py360convert>=1.0.3
Requires-Dist: matplotlib
Requires-Dist: requests
Requires-Dist: wget
Requires-Dist: numpy
Requires-Dist: numpy-quaternion
Requires-Dist: ipywidgets
Requires-Dist: astropy
Requires-Dist: xarray
Requires-Dist: tqdm
Requires-Dist: netcdf4
Dynamic: license-file
